manim_weighted_line/__init__.py
manim_weighted_line/weighted_line.py
manim_weighted_line-0.1.0.dist-info/LICENSE
manim_weighted_line-0.1.0.dist-info/METADATA
manim_weighted_line-0.1.0.dist-info/WHEEL
manim_weighted_line-0.1.0.dist-info/entry_points.txt
manim_weighted_line-0.1.0.dist-info/RECORD
