Metadata-Version: 2.1
Name: manim-weighted-line
Version: 0.1.0
Summary: Adds a weighted line object to use with network graph diagrams.
Home-page: https://github.com/mutable-learning/manim-weighted-line
License: MIT
Keywords: manim,plugins
Author: MutableLearning
Author-email: mutable.learning@gmail.com
Requires-Python: >=3.8,<3.12
Classifier: License :: OSI Approved :: MIT License
Classifier: Programming Language :: Python :: 3
Classifier: Programming Language :: Python :: 3.8
Classifier: Programming Language :: Python :: 3.9
Classifier: Programming Language :: Python :: 3.10
Classifier: Programming Language :: Python :: 3.11
Requires-Dist: manim (>=0.17.3,<0.18.0)
Project-URL: Bug Tracker, https://github.com/mutable-learning/manim-weighted-line/issues
Project-URL: Changelog, https://github.com/mutable-learning/manim-weighted-line/blob/main/CHANGELOG.md
Project-URL: Repository, https://github.com/mutable-learning/manim-weighted-line
